smoltex/__init__.py
smoltex/main.py
smoltex/prompts.py
smoltex/render.py
smoltex-0.2.0.dist-info/LICENSE
smoltex-0.2.0.dist-info/METADATA
smoltex-0.2.0.dist-info/WHEEL
smoltex-0.2.0.dist-info/entry_points.txt
smoltex-0.2.0.dist-info/RECORD
