Metadata-Version: 2.1
Name: smoltex
Version: 0.2.0
Summary: Convert natural language descriptions to LaTeX equations
Author: maharshi
Author-email: maharshi.pandya2002@gmail.com
Requires-Python: >=3.9,<4.0
Classifier: Programming Language :: Python :: 3
Classifier: Programming Language :: Python :: 3.9
Classifier: Programming Language :: Python :: 3.10
Classifier: Programming Language :: Python :: 3.11
Classifier: Programming Language :: Python :: 3.12
Provides-Extra: local
Requires-Dist: groq (>=0.9.0,<0.10.0)
Requires-Dist: llama_cpp_python (>=0.2.82,<0.3.0) ; extra == "local"
Requires-Dist: matplotlib (>=3.9.1,<4.0.0)
Requires-Dist: rich (>=13.7.0,<14.0.0)
Requires-Dist: torch (>=2.3.1,<3.0.0) ; extra == "local"
Requires-Dist: transformers (>=4.42.3,<5.0.0) ; extra == "local"
